multiwallet_gui/__init__.py
multiwallet_gui/about.py
multiwallet_gui/app.py
multiwallet_gui/helper.py
multiwallet_gui/receive.py
multiwallet_gui/seedpicker.py
multiwallet_gui/send.py
multiwallet-0.3.10.dist-info/METADATA
multiwallet-0.3.10.dist-info/WHEEL
multiwallet-0.3.10.dist-info/entry_points.txt
multiwallet-0.3.10.dist-info/top_level.txt
multiwallet-0.3.10.dist-info/RECORD
