Metadata-Version: 2.1
Name: multiwallet
Version: 0.3.10
Summary: Stateless multisig bitcoin wallet
Home-page: https://github.com/mflaxman/multiwallet
Author: Michael Flaxman
Author-email: multiwallet@michaelflaxman.com
License: UNKNOWN
Platform: UNKNOWN
Classifier: Programming Language :: Python :: 3
Classifier: License :: OSI Approved :: MIT License
Classifier: Operating System :: OS Independent
Requires-Python: >=3.6
Requires-Dist: buidl (==0.2.2)
Requires-Dist: PyQt5 (==5.15.1)
Requires-Dist: qrcode (==6.1)
Requires-Dist: Pillow (==8.0.1)
